packege/__init__.py
packege/main.py
packege-0.1.0.dist-info/METADATA
packege-0.1.0.dist-info/WHEEL
packege-0.1.0.dist-info/license
packege-0.1.0.dist-info/top_level.txt
packege-0.1.0.dist-info/RECORD
